picardtools/__init__.py
picardtools/download.py
picardtools/env.py
picardtools/picardtools.py
picardtools-0.1.2.dist-info/LICENSE
picardtools-0.1.2.dist-info/METADATA
picardtools-0.1.2.dist-info/WHEEL
picardtools-0.1.2.dist-info/entry_points.txt
picardtools-0.1.2.dist-info/top_level.txt
picardtools-0.1.2.dist-info/RECORD
