Metadata-Version: 2.1
Name: picardtools
Version: 0.1.2
Summary: python3 interface with Picard Tools from Broad institute
Home-page: https://gitlab.com/aaylward/picardtools
Author: Anthony Aylward
Author-email: aaylward@salk.edu
License: UNKNOWN
Platform: UNKNOWN
Classifier: Programming Language :: Python :: 3
Classifier: License :: OSI Approved :: MIT License
Classifier: Operating System :: OS Independent
License-File: LICENSE
